src/__init__.py
src/analysis.py
src/config.py
src/defaults.py
src/generator.py
src/logger.py
src/text_utils.py
src/transcription.py
src/visualization.py
tests/__init__.py
tests/test_analysis.py
tests/test_config.py
podcast_teaser-0.1.0.dist-info/LICENSE
podcast_teaser-0.1.0.dist-info/METADATA
podcast_teaser-0.1.0.dist-info/WHEEL
podcast_teaser-0.1.0.dist-info/entry_points.txt
podcast_teaser-0.1.0.dist-info/top_level.txt
podcast_teaser-0.1.0.dist-info/RECORD
