Metadata-Version: 2.2
Name: podcast_teaser
Version: 0.1.0
Summary: Automatically generate engaging audio teasers from podcast episodes
Home-page: https://github.com/SharathSPhD/PodcastTeaserGenerator
Author: Podcast Teaser Generator Contributors
Author-email: example@example.com
Classifier: Programming Language :: Python :: 3
Classifier: License :: OSI Approved :: MIT License
Classifier: Operating System :: OS Independent
Classifier: Topic :: Multimedia :: Sound/Audio
Classifier: Topic :: Multimedia :: Sound/Audio :: Analysis
Classifier: Topic :: Multimedia :: Sound/Audio :: Editors
Requires-Python: >=3.7
License-File: LICENSE
Requires-Dist: librosa
Requires-Dist: pydub
Requires-Dist: numpy
Requires-Dist: matplotlib
Requires-Dist: tqdm
Dynamic: author
Dynamic: author-email
Dynamic: classifier
Dynamic: description
Dynamic: description-content-type
Dynamic: home-page
Dynamic: requires-dist
Dynamic: requires-python
Dynamic: summary
